{"metadata":{"usedHelpers":[],"marked":[],"modules":{"imports":[],"exports":{"exported":[],"specifiers":[]}}},"options":{"filename":"/server/publications.js","filenameRelative":"/server/publications.js","env":{},"retainLines":false,"highlightCode":true,"suppressDeprecationMessages":false,"presets":[],"plugins":[[[],{"polyfill":false}],[[],null],[[],null],[[],null],[[],null],[[],null],[[],null],[[],null],[[],null],[[],null],[[],null],[[],null],[[],null],[[],null],[[],{"loose":true}],[[],{"loose":true}],[[],null],[[],{"loose":true}],[[],null],[[],null],[[],null],[[],null],[[],null],[[],null],[[],null],[[],{"loose":true}],[[],null],[[],null],[[],null],[[],null],[[],null],[[],null],[[],null],[[],null]],"ignore":[],"code":true,"metadata":true,"ast":false,"comments":true,"compact":false,"minified":false,"sourceMap":true,"sourceMaps":true,"sourceMapTarget":"/server/publications.js.map","sourceFileName":"/server/publications.js","babelrc":false,"sourceType":"module","moduleIds":false,"passPerPreset":false,"basename":"publications"},"ignored":false,"code":"","ast":null,"map":{"version":3,"sources":[],"names":[],"mappings":"","file":"/server/publications.js.map","sourcesContent":[]},"hash":"b5876772fbd4ea42fe4fcdb1bc3172b1f04186e0"}
